{"cameraMode":{"drawMode":0,"name":"Shaded","section":"Shading Mode"},"sceneLighting":true,"audioPlay":false,"sceneViewState":{"m_AlwaysRefresh":false,"showFog":true,"showSkybox":true,"showFlares":true,"showImageEffects":true,"showParticleSystems":true,"showVisualEffectGraphs":true,"m_FxEnabled":true},"in2DMode":false,"pivot":{"x":-40.099998474121097,"y":59.56206512451172,"z":-10.479251861572266},"rotation":{"x":0.06954137235879898,"y":0.9284857511520386,"z":-0.28752943873405459,"w":0.22456084191799165},"size":2.5186848640441896,"orthographic":false}